mowl/__init__.py
mowl/main.py
mowl/base_models/__init__.py
mowl/base_models/alcmodel.py
mowl/base_models/elmodel.py
mowl/base_models/graph_model.py
mowl/base_models/model.py
mowl/base_models/syntactic_model.py
mowl/corpus/__init__.py
mowl/corpus/base.py
mowl/datasets/__init__.py
mowl/datasets/base.py
mowl/datasets/gci.py
mowl/datasets/alc/__init__.py
mowl/datasets/alc/alc_dataset.py
mowl/datasets/builtin/__init__.py
mowl/datasets/builtin/family.py
mowl/datasets/builtin/gda.py
mowl/datasets/builtin/gda2.py
mowl/datasets/builtin/ppi_yeast.py
mowl/datasets/builtin/subsumption.py
mowl/datasets/el/__init__.py
mowl/datasets/el/el_dataset.py
mowl/error/__init__.py
mowl/error/messages.py
mowl/evaluation/__init__.py
mowl/evaluation/base.py
mowl/evaluation/gda.py
mowl/evaluation/metrics.py
mowl/evaluation/ppi.py
mowl/evaluation/predictions.py
mowl/evaluation/rank_based.py
mowl/evaluation/subsumption.py
mowl/inference/__init__.py
mowl/inference/axiom_scoring.py
mowl/inference/base.py
mowl/inference/cosine.py
mowl/inference/el.py
mowl/kge/__init__.py
mowl/kge/model.py
mowl/lib/apache-mime4j-core-0.7.2.jar
mowl/lib/automaton-1.11-8.jar
mowl/lib/axiom-api-1.2.14.jar
mowl/lib/axiom-c14n-1.2.14.jar
mowl/lib/axiom-dom-1.2.14.jar
mowl/lib/axiom-impl-1.2.14.jar
mowl/lib/caffeine-2.8.6.jar
mowl/lib/checker-qual-3.7.0.jar
mowl/lib/collection-0.7.jar
mowl/lib/commons-beanutils-1.7.0.jar
mowl/lib/commons-beanutils-core-1.8.0.jar
mowl/lib/commons-cli-1.4.jar
mowl/lib/commons-codec-1.15.jar
mowl/lib/commons-collections-3.2.1.jar
mowl/lib/commons-compress-1.20.jar
mowl/lib/commons-configuration-1.6.jar
mowl/lib/commons-csv-1.8.jar
mowl/lib/commons-dbcp-1.3.jar
mowl/lib/commons-digester-1.8.jar
mowl/lib/commons-httpclient-3.1.jar
mowl/lib/commons-io-2.8.0.jar
mowl/lib/commons-lang-2.4.jar
mowl/lib/commons-lang3-3.11.jar
mowl/lib/commons-logging-1.2.jar
mowl/lib/commons-pool-1.5.4.jar
mowl/lib/elk-cli-0.4.3.jar
mowl/lib/elk-distribution-0.4.3.jar
mowl/lib/elk-owl-implementation-0.4.3.jar
mowl_borg-1.0.2.dist-info/licenses/LICENSE
mowl_borg-1.0.2.dist-info/METADATA
mowl_borg-1.0.2.dist-info/WHEEL
mowl_borg-1.0.2.dist-info/top_level.txt
mowl_borg-1.0.2.dist-info/RECORD
