Metadata-Version: 2.4
Name: mowl-borg
Version: 1.0.2
Summary: mOWL: A machine learning library with ontologies
Home-page: https://github.com/bio-ontology-research-group/mowl
Author: Bio-Ontology Research Group
Author-email: fernando.zhapacamacho@kaust.edu.sa
Project-URL: Bug Tracker, https://github.com/bio-ontology-research-group/mowl/issues
Classifier: Programming Language :: Python :: 3
Classifier: License :: OSI Approved :: BSD License
Classifier: Operating System :: OS Independent
Requires-Python: >=3.9
License-File: LICENSE
Requires-Dist: class-resolver==0.5.4
Requires-Dist: click
Requires-Dist: deprecated
Requires-Dist: gensim>=4.3.0
Requires-Dist: JPype1==1.5.1
Requires-Dist: matplotlib
Requires-Dist: networkx
Requires-Dist: numpy
Requires-Dist: pandas
Requires-Dist: pykeen==1.11.0
Requires-Dist: pyyaml
Requires-Dist: requests
Requires-Dist: scikit-learn
Requires-Dist: scipy<1.16.0
Requires-Dist: temp
Requires-Dist: tqdm
Requires-Dist: torch
Requires-Dist: urllib3
Dynamic: author
Dynamic: author-email
Dynamic: classifier
Dynamic: description
Dynamic: description-content-type
Dynamic: home-page
Dynamic: license-file
Dynamic: project-url
Dynamic: requires-dist
Dynamic: requires-python
Dynamic: summary
